pviewer/__init__.py
pviewer/__main__.py
pviewer-1.0.dist-info/LICENSE.txt
pviewer-1.0.dist-info/METADATA
pviewer-1.0.dist-info/WHEEL
pviewer-1.0.dist-info/entry_points.txt
pviewer-1.0.dist-info/top_level.txt
pviewer-1.0.dist-info/RECORD
