Metadata-Version: 2.1
Name: pviewer
Version: 1.0
Summary: pviewer is a tool which will be used to find the conflicting policies for a AWS IAM user
Home-page: https://github.com/ankitsaini2609/PViewer
Author: Ankit Saini
Author-email: ankitsaini2609@gmail.com
License: MIT
Platform: UNKNOWN
Classifier: License :: OSI Approved :: MIT License
Classifier: Programming Language :: Python :: 3
Requires-Dist: boto3
Requires-Dist: graphviz
Requires-Dist: pytest
